{"languages": ["es", "en", "ca"], "name_es": "TerminalSpringApp", "banner_es": "TerminalSpring2DApp.png", "html_es": "TerminalSpring2DApp-es.html", "name_en": "TerminalSpringApp", "banner_en": "TerminalSpring2DApp.png", "html_en": "TerminalSpring2DApp-en.html", "name_ca": "TerminalSpringApp", "banner_ca": "TerminalSpring2DApp.png", "html_ca": "TerminalSpring2DApp-ca.html", "category": "physics", "require": "", "license": "Apache-2.0", "url": "https://github.com/myphysicslab/myphysicslab", "description": "Real-time interactive animated physics simulations"}